{
  "ogmoVersion": "3.4.0-hubol",
  "width": 500,
  "height": 1672,
  "offsetX": 0,
  "offsetY": 0,
  "values": {"Terrain Color": "#000000"},
  "backgroundColor": "#408000",
  "layers": [
    {
      "name": "MarkerEntities",
      "_eid": "73166939",
      "offsetX": 0,
      "offsetY": 0,
      "gridCellWidth": 8,
      "gridCellHeight": 8,
      "gridCellsX": 64,
      "gridCellsY": 209,
      "entities": []
    },
    {
      "name": "RegionEntities",
      "_eid": "01831167",
      "offsetX": 0,
      "offsetY": 0,
      "gridCellWidth": 8,
      "gridCellHeight": 8,
      "gridCellsX": 64,
      "gridCellsY": 209,
      "entities": []
    },
    {
      "name": "FrontDecals",
      "_eid": "17577176",
      "offsetX": 0,
      "offsetY": 0,
      "gridCellWidth": 8,
      "gridCellHeight": 8,
      "gridCellsX": 64,
      "gridCellsY": 209,
      "decals": [],
      "folder": "../textures"
    },
    {
      "name": "FrontEntities",
      "_eid": "55690179",
      "offsetX": 0,
      "offsetY": 0,
      "gridCellWidth": 8,
      "gridCellHeight": 8,
      "gridCellsX": 64,
      "gridCellsY": 209,
      "entities": []
    },
    {
      "name": "PlayerEntities",
      "_eid": "96470627",
      "offsetX": 0,
      "offsetY": 0,
      "gridCellWidth": 8,
      "gridCellHeight": 8,
      "gridCellsX": 64,
      "gridCellsY": 209,
      "entities": [
        {
          "name": "Player",
          "id": 0,
          "_eid": "93092164",
          "x": 88,
          "y": 1640,
          "originX": 22,
          "originY": 39,
          "flippedX": false,
          "values": {"name": "", "depth": 0}
        },
        {
          "name": "Checkpoint",
          "id": 1,
          "_eid": "19953026",
          "x": 80,
          "y": 1488,
          "originX": 22,
          "originY": 39,
          "flippedX": false,
          "values": {"name": "wrong0", "depth": 0, "overrideFlipX": "none"}
        },
        {
          "name": "Checkpoint",
          "id": 2,
          "_eid": "19953026",
          "x": 80,
          "y": 1328,
          "originX": 22,
          "originY": 39,
          "flippedX": false,
          "values": {"name": "wrong1", "depth": 0, "overrideFlipX": "none"}
        },
        {
          "name": "Checkpoint",
          "id": 3,
          "_eid": "19953026",
          "x": 80,
          "y": 1168,
          "originX": 22,
          "originY": 39,
          "flippedX": false,
          "values": {"name": "level1", "depth": 0, "overrideFlipX": "none"}
        },
        {
          "name": "Checkpoint",
          "id": 4,
          "_eid": "19953026",
          "x": 80,
          "y": 1000,
          "originX": 22,
          "originY": 39,
          "flippedX": false,
          "values": {"name": "level2", "depth": 0, "overrideFlipX": "none"}
        },
        {
          "name": "Checkpoint",
          "id": 5,
          "_eid": "19953026",
          "x": 80,
          "y": 832,
          "originX": 22,
          "originY": 39,
          "flippedX": false,
          "values": {"name": "level3", "depth": 0, "overrideFlipX": "none"}
        },
        {
          "name": "Checkpoint",
          "id": 6,
          "_eid": "19953026",
          "x": 80,
          "y": 664,
          "originX": 22,
          "originY": 39,
          "flippedX": false,
          "values": {"name": "level4", "depth": 0, "overrideFlipX": "none"}
        },
        {
          "name": "Checkpoint",
          "id": 7,
          "_eid": "19953026",
          "x": 80,
          "y": 480,
          "originX": 22,
          "originY": 39,
          "flippedX": false,
          "values": {"name": "level5", "depth": 0, "overrideFlipX": "none"}
        },
        {
          "name": "Checkpoint",
          "id": 8,
          "_eid": "19953026",
          "x": 80,
          "y": 328,
          "originX": 22,
          "originY": 39,
          "flippedX": false,
          "values": {"name": "midboss0", "depth": 0, "overrideFlipX": "none"}
        }
      ]
    },
    {
      "name": "CharacterEntities",
      "_eid": "07790422",
      "offsetX": 0,
      "offsetY": 0,
      "gridCellWidth": 8,
      "gridCellHeight": 8,
      "gridCellsX": 64,
      "gridCellsY": 209,
      "entities": []
    },
    {
      "name": "AboveEntitiesDecals",
      "_eid": "63753160",
      "offsetX": 0,
      "offsetY": 0,
      "gridCellWidth": 8,
      "gridCellHeight": 8,
      "gridCellsX": 64,
      "gridCellsY": 209,
      "decals": [],
      "folder": "../textures"
    },
    {
      "name": "Entities",
      "_eid": "93086020",
      "offsetX": 0,
      "offsetY": 0,
      "gridCellWidth": 8,
      "gridCellHeight": 8,
      "gridCellsX": 64,
      "gridCellsY": 209,
      "entities": [
        {
          "name": "Door",
          "id": 0,
          "_eid": "88296692",
          "x": 160,
          "y": 1592,
          "originX": 0,
          "originY": -2,
          "values": {"sceneName": "scnIntelligenceTower", "checkpointName": "wrong0", "name": "", "depth": 0}
        },
        {
          "name": "Door",
          "id": 1,
          "_eid": "88296692",
          "x": 232,
          "y": 1592,
          "originX": 0,
          "originY": -2,
          "values": {"sceneName": "scnIntelligenceTower", "checkpointName": "level1", "name": "", "depth": 0}
        },
        {
          "name": "Door",
          "id": 2,
          "_eid": "88296692",
          "x": 296,
          "y": 1592,
          "originX": 0,
          "originY": -2,
          "values": {"sceneName": "scnIntelligenceTower", "checkpointName": "wrong0", "name": "", "depth": 0}
        },
        {
          "name": "Door",
          "id": 3,
          "_eid": "88296692",
          "x": 360,
          "y": 1592,
          "originX": 0,
          "originY": -2,
          "values": {"sceneName": "scnIntelligenceTower", "checkpointName": "wrong1", "name": "", "depth": 0}
        },
        {
          "name": "Door",
          "id": 4,
          "_eid": "88296692",
          "x": 160,
          "y": 1440,
          "originX": 0,
          "originY": -2,
          "values": {"sceneName": "scnIntelligenceTower", "checkpointName": "level0", "name": "", "depth": 0}
        },
        {
          "name": "Door",
          "id": 5,
          "_eid": "88296692",
          "x": 232,
          "y": 1440,
          "originX": 0,
          "originY": -2,
          "values": {"sceneName": "scnIntelligenceTower", "checkpointName": "level0", "name": "", "depth": 0}
        },
        {
          "name": "Door",
          "id": 6,
          "_eid": "88296692",
          "x": 296,
          "y": 1440,
          "originX": 0,
          "originY": -2,
          "values": {"sceneName": "scnIntelligenceTower", "checkpointName": "level0", "name": "", "depth": 0}
        },
        {
          "name": "Door",
          "id": 7,
          "_eid": "88296692",
          "x": 360,
          "y": 1440,
          "originX": 0,
          "originY": -2,
          "values": {"sceneName": "scnIntelligenceTower", "checkpointName": "level0", "name": "", "depth": 0}
        },
        {
          "name": "Door",
          "id": 8,
          "_eid": "88296692",
          "x": 160,
          "y": 1280,
          "originX": 0,
          "originY": -2,
          "values": {"sceneName": "scnIntelligenceTower", "checkpointName": "level0", "name": "", "depth": 0}
        },
        {
          "name": "Door",
          "id": 9,
          "_eid": "88296692",
          "x": 232,
          "y": 1280,
          "originX": 0,
          "originY": -2,
          "values": {"sceneName": "scnIntelligenceTower", "checkpointName": "level0", "name": "", "depth": 0}
        },
        {
          "name": "Door",
          "id": 10,
          "_eid": "88296692",
          "x": 296,
          "y": 1280,
          "originX": 0,
          "originY": -2,
          "values": {"sceneName": "scnIntelligenceTower", "checkpointName": "level0", "name": "", "depth": 0}
        },
        {
          "name": "Door",
          "id": 11,
          "_eid": "88296692",
          "x": 360,
          "y": 1280,
          "originX": 0,
          "originY": -2,
          "values": {"sceneName": "scnIntelligenceTower", "checkpointName": "level0", "name": "", "depth": 0}
        },
        {
          "name": "Door",
          "id": 12,
          "_eid": "88296692",
          "x": 160,
          "y": 1120,
          "originX": 0,
          "originY": -2,
          "values": {"sceneName": "scnIntelligenceTower", "checkpointName": "wrong1", "name": "TimeCheck6Door", "depth": 0}
        },
        {
          "name": "Door",
          "id": 13,
          "_eid": "88296692",
          "x": 232,
          "y": 1120,
          "originX": 0,
          "originY": -2,
          "values": {"sceneName": "scnIntelligenceTower", "checkpointName": "wrong0", "name": "TimeCheck3Door", "depth": 0}
        },
        {
          "name": "Door",
          "id": 14,
          "_eid": "88296692",
          "x": 296,
          "y": 1120,
          "originX": 0,
          "originY": -2,
          "values": {"sceneName": "scnIntelligenceTower", "checkpointName": "wrong1", "name": "TimeCheck12Door", "depth": 0}
        },
        {
          "name": "Door",
          "id": 15,
          "_eid": "88296692",
          "x": 360,
          "y": 1120,
          "originX": 0,
          "originY": -2,
          "values": {"sceneName": "scnIntelligenceTower", "checkpointName": "level0", "name": "TimeCheck9Door", "depth": 0}
        },
        {
          "name": "IntelligenceBackground",
          "id": 16,
          "_eid": "41461695",
          "x": 432,
          "y": 1360,
          "width": 72,
          "height": 216,
          "originX": 0,
          "originY": 0,
          "values": {"initialTint": "#000000", "targetTint": "#808080", "min": 1, "max": 5, "name": "", "depth": 0}
        },
        {
          "name": "IntelligenceSign",
          "id": 17,
          "_eid": "61823517",
          "x": 408,
          "y": 1168,
          "originX": 0,
          "originY": 26,
          "values": {"title": "Clock", "message": "D at 12 o' clock. E at 3 o' clock. F at 6 o' clock. G at 9 o' clock.", "min": 1, "max": 2, "name": "", "depth": 0}
        },
        {
          "name": "IntelligenceSign",
          "id": 18,
          "_eid": "61823517",
          "x": 408,
          "y": 1000,
          "originX": 0,
          "originY": 26,
          "values": {"title": "Meal", "message": "Spell \"meal\".", "min": 2, "max": 3, "name": "", "depth": 0}
        },
        {
          "name": "Door",
          "id": 19,
          "_eid": "88296692",
          "x": 168,
          "y": 952,
          "originX": 0,
          "originY": -2,
          "values": {"sceneName": "scnIntelligenceTower", "checkpointName": "wrong1", "name": "", "depth": 0}
        },
        {
          "name": "Door",
          "id": 20,
          "_eid": "88296692",
          "x": 232,
          "y": 952,
          "originX": 0,
          "originY": -2,
          "values": {"sceneName": "scnIntelligenceTower", "checkpointName": "wrong0", "name": "", "depth": 0}
        },
        {
          "name": "Door",
          "id": 21,
          "_eid": "88296692",
          "x": 296,
          "y": 952,
          "originX": 0,
          "originY": -2,
          "values": {"sceneName": "scnIntelligenceTower", "checkpointName": "level3", "name": "", "depth": 0}
        },
        {
          "name": "Door",
          "id": 22,
          "_eid": "88296692",
          "x": 360,
          "y": 952,
          "originX": 0,
          "originY": -2,
          "values": {"sceneName": "scnIntelligenceTower", "checkpointName": "level0", "name": "", "depth": 0}
        },
        {
          "name": "Door",
          "id": 23,
          "_eid": "88296692",
          "x": 160,
          "y": 784,
          "originX": 0,
          "originY": -2,
          "values": {"sceneName": "scnIntelligenceTower", "checkpointName": "level4", "name": "", "depth": 0}
        },
        {
          "name": "Door",
          "id": 24,
          "_eid": "88296692",
          "x": 232,
          "y": 784,
          "originX": 0,
          "originY": -2,
          "values": {"sceneName": "scnIntelligenceTower", "checkpointName": "wrong0", "name": "", "depth": 0}
        },
        {
          "name": "Door",
          "id": 25,
          "_eid": "88296692",
          "x": 296,
          "y": 784,
          "originX": 0,
          "originY": -2,
          "values": {"sceneName": "scnIntelligenceTower", "checkpointName": "wrong1", "name": "", "depth": 0}
        },
        {
          "name": "Door",
          "id": 26,
          "_eid": "88296692",
          "x": 360,
          "y": 784,
          "originX": 0,
          "originY": -2,
          "values": {"sceneName": "scnIntelligenceTower", "checkpointName": "wrong0", "name": "", "depth": 0}
        },
        {
          "name": "Door",
          "id": 27,
          "_eid": "88296692",
          "x": 160,
          "y": 616,
          "originX": 0,
          "originY": -2,
          "values": {"sceneName": "scnIntelligenceTower", "checkpointName": "level2", "name": "", "depth": 0}
        },
        {
          "name": "Door",
          "id": 28,
          "_eid": "88296692",
          "x": 232,
          "y": 616,
          "originX": 0,
          "originY": -2,
          "values": {"sceneName": "scnIntelligenceTower", "checkpointName": "wrong1", "name": "", "depth": 0}
        },
        {
          "name": "Door",
          "id": 29,
          "_eid": "88296692",
          "x": 296,
          "y": 616,
          "originX": 0,
          "originY": -2,
          "values": {"sceneName": "scnIntelligenceTower", "checkpointName": "wrong1", "name": "", "depth": 0}
        },
        {
          "name": "Door",
          "id": 30,
          "_eid": "88296692",
          "x": 360,
          "y": 616,
          "originX": 0,
          "originY": -2,
          "values": {"sceneName": "scnIntelligenceTower", "checkpointName": "level5", "name": "", "depth": 0}
        },
        {
          "name": "Door",
          "id": 31,
          "_eid": "88296692",
          "x": 160,
          "y": 432,
          "originX": 0,
          "originY": -2,
          "values": {"sceneName": "scnIntelligenceTower", "checkpointName": "level1", "name": "", "depth": 0}
        },
        {
          "name": "Door",
          "id": 32,
          "_eid": "88296692",
          "x": 232,
          "y": 432,
          "originX": 0,
          "originY": -2,
          "values": {"sceneName": "scnIntelligenceTower", "checkpointName": "midboss0", "name": "", "depth": 0}
        },
        {
          "name": "Door",
          "id": 33,
          "_eid": "88296692",
          "x": 296,
          "y": 432,
          "originX": 0,
          "originY": -2,
          "values": {"sceneName": "scnIntelligenceTower", "checkpointName": "wrong1", "name": "", "depth": 0}
        },
        {
          "name": "Door",
          "id": 34,
          "_eid": "88296692",
          "x": 360,
          "y": 432,
          "originX": 0,
          "originY": -2,
          "values": {"sceneName": "scnIntelligenceTower", "checkpointName": "level2", "name": "", "depth": 0}
        },
        {
          "name": "EnemyChill",
          "id": 35,
          "_eid": "53690151",
          "x": 248,
          "y": 272,
          "originX": 45,
          "originY": 105,
          "values": {"variant": "level1", "name": "", "depth": 0}
        }
      ]
    },
    {
      "name": "TerrainDecals",
      "_eid": "02386446",
      "offsetX": 0,
      "offsetY": 0,
      "gridCellWidth": 8,
      "gridCellHeight": 8,
      "gridCellsX": 64,
      "gridCellsY": 209,
      "decals": [],
      "folder": "../textures"
    },
    {
      "name": "TerrainEntities",
      "_eid": "02302709",
      "offsetX": 0,
      "offsetY": 0,
      "gridCellWidth": 8,
      "gridCellHeight": 8,
      "gridCellsX": 64,
      "gridCellsY": 209,
      "entities": [
        {
          "name": "Block",
          "id": 0,
          "_eid": "93117141",
          "x": 0,
          "y": 1280,
          "width": 32,
          "height": 280,
          "originX": 0,
          "originY": 0,
          "tint": "#000000",
          "values": {"name": "", "depth": 0, "visible": true}
        },
        {
          "name": "Block",
          "id": 1,
          "_eid": "93117141",
          "x": 472,
          "y": 1280,
          "width": 40,
          "height": 136,
          "originX": 0,
          "originY": 0,
          "tint": "#000000",
          "values": {"name": "", "depth": 0, "visible": true}
        },
        {
          "name": "Block",
          "id": 2,
          "_eid": "93117141",
          "x": 0,
          "y": 1640,
          "width": 512,
          "height": 32,
          "originX": 0,
          "originY": 0,
          "tint": "#000000",
          "values": {"name": "", "depth": 0, "visible": true}
        },
        {
          "name": "Block",
          "id": 3,
          "_eid": "93117141",
          "x": 32,
          "y": 1488,
          "width": 72,
          "height": 72,
          "originX": 0,
          "originY": 0,
          "tint": "#000000",
          "values": {"name": "", "depth": 0, "visible": true}
        },
        {
          "name": "Block",
          "id": 4,
          "_eid": "93117141",
          "x": 104,
          "y": 1488,
          "width": 328,
          "height": 32,
          "originX": 0,
          "originY": 0,
          "tint": "#000000",
          "values": {"name": "", "depth": 0, "visible": true}
        },
        {
          "name": "Block",
          "id": 5,
          "_eid": "93117141",
          "x": 32,
          "y": 1328,
          "width": 72,
          "height": 72,
          "originX": 0,
          "originY": 0,
          "tint": "#000000",
          "values": {"name": "", "depth": 0, "visible": true}
        },
        {
          "name": "Block",
          "id": 6,
          "_eid": "93117141",
          "x": 104,
          "y": 1328,
          "width": 512,
          "height": 32,
          "originX": 0,
          "originY": 0,
          "tint": "#000000",
          "values": {"name": "", "depth": 0, "visible": true}
        },
        {
          "name": "Block",
          "id": 7,
          "_eid": "93117141",
          "x": 0,
          "y": 1120,
          "width": 32,
          "height": 280,
          "originX": 0,
          "originY": 0,
          "tint": "#000000",
          "values": {"name": "", "depth": 0, "visible": true}
        },
        {
          "name": "Block",
          "id": 8,
          "_eid": "93117141",
          "x": 472,
          "y": 1120,
          "width": 40,
          "height": 136,
          "originX": 0,
          "originY": 0,
          "tint": "#000000",
          "values": {"name": "", "depth": 0, "visible": true}
        },
        {
          "name": "Block",
          "id": 9,
          "_eid": "93117141",
          "x": 32,
          "y": 1168,
          "width": 72,
          "height": 72,
          "originX": 0,
          "originY": 0,
          "tint": "#000000",
          "values": {"name": "", "depth": 0, "visible": true}
        },
        {
          "name": "Block",
          "id": 10,
          "_eid": "93117141",
          "x": 104,
          "y": 1168,
          "width": 512,
          "height": 32,
          "originX": 0,
          "originY": 0,
          "tint": "#000000",
          "values": {"name": "", "depth": 0, "visible": true}
        },
        {
          "name": "Block",
          "id": 12,
          "_eid": "93117141",
          "x": 408,
          "y": 1360,
          "width": 24,
          "height": 128,
          "originX": 0,
          "originY": 0,
          "tint": "#000000",
          "values": {"name": "", "depth": 0, "visible": true}
        },
        {
          "name": "Block",
          "id": 14,
          "_eid": "93117141",
          "x": 432,
          "y": 1504,
          "width": 32,
          "height": 16,
          "originX": 0,
          "originY": 0,
          "tint": "#000000",
          "values": {"name": "", "depth": 0, "visible": true}
        },
        {
          "name": "Block",
          "id": 15,
          "_eid": "93117141",
          "x": 432,
          "y": 1576,
          "width": 72,
          "height": 64,
          "originX": 0,
          "originY": 0,
          "tint": "#000000",
          "values": {"name": "", "depth": 0, "visible": true}
        },
        {
          "name": "Block",
          "id": 16,
          "_eid": "93117141",
          "x": 0,
          "y": 840,
          "width": 32,
          "height": 280,
          "originX": 0,
          "originY": 0,
          "tint": "#000000",
          "values": {"name": "", "depth": 0, "visible": true}
        },
        {
          "name": "Block",
          "id": 17,
          "_eid": "93117141",
          "x": 472,
          "y": 840,
          "width": 32,
          "height": 280,
          "originX": 0,
          "originY": 0,
          "tint": "#000000",
          "values": {"name": "", "depth": 0, "visible": true}
        },
        {
          "name": "Block",
          "id": 18,
          "_eid": "93117141",
          "x": 32,
          "y": 1000,
          "width": 512,
          "height": 32,
          "originX": 0,
          "originY": 0,
          "tint": "#000000",
          "values": {"name": "", "depth": 0, "visible": true}
        },
        {
          "name": "Block",
          "id": 19,
          "_eid": "93117141",
          "x": 0,
          "y": 672,
          "width": 32,
          "height": 280,
          "originX": 0,
          "originY": 0,
          "tint": "#000000",
          "values": {"name": "", "depth": 0, "visible": true}
        },
        {
          "name": "Block",
          "id": 20,
          "_eid": "93117141",
          "x": 472,
          "y": 672,
          "width": 32,
          "height": 280,
          "originX": 0,
          "originY": 0,
          "tint": "#000000",
          "values": {"name": "", "depth": 0, "visible": true}
        },
        {
          "name": "Block",
          "id": 21,
          "_eid": "93117141",
          "x": 32,
          "y": 832,
          "width": 512,
          "height": 32,
          "originX": 0,
          "originY": 0,
          "tint": "#000000",
          "values": {"name": "", "depth": 0, "visible": true}
        },
        {
          "name": "Block",
          "id": 22,
          "_eid": "93117141",
          "x": 0,
          "y": 504,
          "width": 32,
          "height": 280,
          "originX": 0,
          "originY": 0,
          "tint": "#000000",
          "values": {"name": "", "depth": 0, "visible": true}
        },
        {
          "name": "Block",
          "id": 23,
          "_eid": "93117141",
          "x": 472,
          "y": 504,
          "width": 32,
          "height": 280,
          "originX": 0,
          "originY": 0,
          "tint": "#000000",
          "values": {"name": "", "depth": 0, "visible": true}
        },
        {
          "name": "Block",
          "id": 24,
          "_eid": "93117141",
          "x": 32,
          "y": 664,
          "width": 512,
          "height": 32,
          "originX": 0,
          "originY": 0,
          "tint": "#000000",
          "values": {"name": "", "depth": 0, "visible": true}
        },
        {
          "name": "Block",
          "id": 28,
          "_eid": "93117141",
          "x": 0,
          "y": 320,
          "width": 32,
          "height": 280,
          "originX": 0,
          "originY": 0,
          "tint": "#000000",
          "values": {"name": "", "depth": 0, "visible": true}
        },
        {
          "name": "Block",
          "id": 29,
          "_eid": "93117141",
          "x": 472,
          "y": 320,
          "width": 32,
          "height": 280,
          "originX": 0,
          "originY": 0,
          "tint": "#000000",
          "values": {"name": "", "depth": 0, "visible": true}
        },
        {
          "name": "Block",
          "id": 30,
          "_eid": "93117141",
          "x": 32,
          "y": 480,
          "width": 512,
          "height": 32,
          "originX": 0,
          "originY": 0,
          "tint": "#000000",
          "values": {"name": "", "depth": 0, "visible": true}
        },
        {
          "name": "Block",
          "id": 31,
          "_eid": "93117141",
          "x": 0,
          "y": 40,
          "width": 32,
          "height": 280,
          "originX": 0,
          "originY": 0,
          "tint": "#000000",
          "values": {"name": "", "depth": 0, "visible": true}
        },
        {
          "name": "Block",
          "id": 32,
          "_eid": "93117141",
          "x": 472,
          "y": 40,
          "width": 32,
          "height": 280,
          "originX": 0,
          "originY": 0,
          "tint": "#000000",
          "values": {"name": "", "depth": 0, "visible": true}
        },
        {
          "name": "Block",
          "id": 33,
          "_eid": "93117141",
          "x": 32,
          "y": 328,
          "width": 512,
          "height": 32,
          "originX": 0,
          "originY": 0,
          "tint": "#000000",
          "values": {"name": "", "depth": 0, "visible": true}
        },
        {
          "name": "Block",
          "id": 34,
          "_eid": "93117141",
          "x": 160,
          "y": 272,
          "width": 176,
          "height": 24,
          "originX": 0,
          "originY": 0,
          "tint": "#000000",
          "values": {"name": "", "depth": 0, "visible": true}
        },
        {
          "name": "Pipe",
          "id": 35,
          "_eid": "95769929",
          "x": 368,
          "y": 272,
          "width": 32,
          "values": {"name": "Midboss0Pipe0", "visible": true, "depth": 0}
        },
        {
          "name": "Pipe",
          "id": 36,
          "_eid": "95769929",
          "x": 96,
          "y": 272,
          "width": 32,
          "values": {"name": "Midboss0Pipe1", "visible": true, "depth": 0}
        },
        {
          "name": "Pipe",
          "id": 37,
          "_eid": "95769929",
          "x": 128,
          "y": 208,
          "width": 32,
          "values": {"name": "Midboss0Pipe2", "visible": true, "depth": 0}
        },
        {
          "name": "Pipe",
          "id": 38,
          "_eid": "95769929",
          "x": 336,
          "y": 208,
          "width": 32,
          "values": {"name": "Midboss0Pipe3", "visible": true, "depth": 0}
        }
      ]
    },
    {
      "name": "BackgroundEntities",
      "_eid": "41483982",
      "offsetX": 0,
      "offsetY": 0,
      "gridCellWidth": 8,
      "gridCellHeight": 8,
      "gridCellsX": 64,
      "gridCellsY": 209,
      "entities": [
        {
          "name": "Clock",
          "id": 0,
          "_eid": "37539959",
          "x": 104,
          "y": 1432,
          "originX": 21,
          "originY": 20,
          "values": {"hours": 6, "minutes": 7, "name": "", "depth": 0}
        },
        {
          "name": "Clock",
          "id": 1,
          "_eid": "37539959",
          "x": 112,
          "y": 1088,
          "originX": 21,
          "originY": 20,
          "values": {"hours": 7, "minutes": 0, "name": "TimeCheckClock", "depth": 0}
        },
        {
          "name": "Dial",
          "id": 2,
          "_eid": "44270482",
          "x": 440,
          "y": 304,
          "originX": 15,
          "originY": 15,
          "values": {"maxTicks": 60, "name": "MidbossDial0", "depth": 0}
        }
      ]
    },
    {
      "name": "BackgroundDecals",
      "_eid": "64691217",
      "offsetX": 0,
      "offsetY": 0,
      "gridCellWidth": 8,
      "gridCellHeight": 8,
      "gridCellsX": 64,
      "gridCellsY": 209,
      "decals": [
        {
          "x": 176,
          "y": 1539,
          "scaleX": 1,
          "scaleY": 1,
          "rotation": 0,
          "tint": "#ffffff",
          "texture": "shapes/fonts/weight3/a.png",
          "originX": 0.5,
          "originY": 0.5,
          "values": {"name": ""},
          "groupName": null
        },
        {
          "x": 248,
          "y": 1539,
          "scaleX": 1,
          "scaleY": 1,
          "rotation": 0,
          "tint": "#ffffff",
          "texture": "shapes/fonts/weight3/b.png",
          "originX": 0.5,
          "originY": 0.5,
          "values": {"name": ""},
          "groupName": null
        },
        {
          "x": 312,
          "y": 1541,
          "scaleX": 1,
          "scaleY": 1,
          "rotation": 0,
          "tint": "#ffffff",
          "texture": "shapes/fonts/weight3/c.png",
          "originX": 0.5,
          "originY": 0.5,
          "values": {"name": ""},
          "groupName": null
        },
        {
          "x": 376,
          "y": 1539,
          "scaleX": -1,
          "scaleY": 1,
          "rotation": 0,
          "tint": "#ffffff",
          "texture": "shapes/fonts/weight3/b.png",
          "originX": 0.5,
          "originY": 0.5,
          "values": {"name": ""},
          "groupName": null
        },
        {
          "x": 176,
          "y": 1573,
          "scaleX": 1,
          "scaleY": 1,
          "rotation": 0,
          "tint": "#ffffff",
          "texture": "shapes/fonts/rune3/a.png",
          "originX": 0.5,
          "originY": 0.5,
          "values": {"name": ""},
          "groupName": null
        },
        {
          "x": 312,
          "y": 1573,
          "scaleX": 1,
          "scaleY": 1,
          "rotation": 0,
          "tint": "#ffffff",
          "texture": "shapes/fonts/rune3/c.png",
          "originX": 0.5,
          "originY": 0.5,
          "values": {"name": ""},
          "groupName": null
        },
        {
          "x": 376,
          "y": 1573,
          "scaleX": 1,
          "scaleY": 1,
          "rotation": 0,
          "tint": "#ffffff",
          "texture": "shapes/fonts/rune3/d.png",
          "originX": 0.5,
          "originY": 0.5,
          "values": {"name": ""},
          "groupName": null
        },
        {
          "x": 376,
          "y": 1384,
          "scaleX": 1,
          "scaleY": 1,
          "rotation": 0,
          "tint": "#ffffff",
          "texture": "shapes/fonts/weight3/e.png",
          "originX": 0.5,
          "originY": 0.5,
          "values": {"name": ""},
          "groupName": null
        },
        {
          "x": 176,
          "y": 1384,
          "scaleX": 1,
          "scaleY": 1,
          "rotation": 0,
          "tint": "#ffffff",
          "texture": "shapes/fonts/weight3/h.png",
          "originX": 0.5,
          "originY": 0.5,
          "values": {"name": ""},
          "groupName": null
        },
        {
          "x": 317,
          "y": 1383,
          "scaleX": 1,
          "scaleY": 1,
          "rotation": 0,
          "tint": "#ffffff",
          "texture": "shapes/fonts/weight3/f.png",
          "originX": 0.5,
          "originY": 0.5,
          "values": {"name": ""},
          "groupName": null
        },
        {
          "x": 248,
          "y": 1387,
          "scaleX": 1,
          "scaleY": 1,
          "rotation": 0,
          "tint": "#ffffff",
          "texture": "shapes/fonts/weight3/g.png",
          "originX": 0.5,
          "originY": 0.5,
          "values": {"name": ""},
          "groupName": null
        },
        {
          "x": 378,
          "y": 1416,
          "scaleX": 1,
          "scaleY": 1,
          "rotation": 0,
          "tint": "#ffffff",
          "texture": "shapes/fonts/rune3/e.png",
          "originX": 0.5,
          "originY": 0.5,
          "values": {"name": ""},
          "groupName": null
        },
        {
          "x": 315,
          "y": 1417,
          "scaleX": 1,
          "scaleY": 1,
          "rotation": 0,
          "tint": "#ffffff",
          "texture": "shapes/fonts/rune3/f.png",
          "originX": 0.5,
          "originY": 0.5,
          "values": {"name": ""},
          "groupName": null
        },
        {
          "x": 250,
          "y": 1422,
          "scaleX": 1,
          "scaleY": 1,
          "rotation": 0,
          "tint": "#ffffff",
          "texture": "shapes/fonts/rune3/g.png",
          "originX": 0.5,
          "originY": 0.5,
          "values": {"name": ""},
          "groupName": null
        },
        {
          "x": 176,
          "y": 1420,
          "scaleX": 1,
          "scaleY": 1,
          "rotation": 0,
          "tint": "#ffffff",
          "texture": "shapes/fonts/rune3/h.png",
          "originX": 0.5,
          "originY": 0.5,
          "values": {"name": ""},
          "groupName": null
        },
        {
          "x": 176,
          "y": 1088,
          "scaleX": 1,
          "scaleY": 1,
          "rotation": 0,
          "tint": "#ffffff",
          "texture": "shapes/fonts/rune3/f.png",
          "originX": 0.5,
          "originY": 0.5,
          "values": {"name": ""},
          "groupName": null
        },
        {
          "x": 248,
          "y": 1088,
          "scaleX": 1,
          "scaleY": 1,
          "rotation": 0,
          "tint": "#ffffff",
          "texture": "shapes/fonts/rune3/e.png",
          "originX": 0.5,
          "originY": 0.5,
          "values": {"name": ""},
          "groupName": null
        },
        {
          "x": 312,
          "y": 1088,
          "scaleX": 1,
          "scaleY": 1,
          "rotation": 0,
          "tint": "#ffffff",
          "texture": "shapes/fonts/rune3/d.png",
          "originX": 0.5,
          "originY": 0.5,
          "values": {"name": ""},
          "groupName": null
        },
        {
          "x": 376,
          "y": 1088,
          "scaleX": 1,
          "scaleY": 1,
          "rotation": 0,
          "tint": "#ffffff",
          "texture": "shapes/fonts/rune3/g.png",
          "originX": 0.5,
          "originY": 0.5,
          "values": {"name": ""},
          "groupName": null
        },
        {
          "x": 176,
          "y": 1225,
          "scaleX": 1,
          "scaleY": 1,
          "rotation": 0,
          "tint": "#ffffff",
          "texture": "shapes/fonts/weight3/i.png",
          "originX": 0.5,
          "originY": 0.5,
          "values": {"name": ""},
          "groupName": null
        },
        {
          "x": 312,
          "y": 1221,
          "scaleX": 1,
          "scaleY": 1,
          "rotation": 0,
          "tint": "#ffffff",
          "texture": "shapes/fonts/weight3/k.png",
          "originX": 0.5,
          "originY": 0.5,
          "values": {"name": ""},
          "groupName": null
        },
        {
          "x": 377,
          "y": 1224,
          "scaleX": 1,
          "scaleY": 1,
          "rotation": 0,
          "tint": "#ffffff",
          "texture": "shapes/fonts/weight3/l.png",
          "originX": 0.5,
          "originY": 0.5,
          "values": {"name": ""},
          "groupName": null
        },
        {
          "x": 176,
          "y": 1256,
          "scaleX": 1,
          "scaleY": 1,
          "rotation": 0,
          "tint": "#ffffff",
          "texture": "shapes/fonts/rune3/i.png",
          "originX": 0.5,
          "originY": 0.5,
          "values": {"name": ""},
          "groupName": null
        },
        {
          "x": 245,
          "y": 1256,
          "scaleX": 1,
          "scaleY": 1,
          "rotation": 0,
          "tint": "#ffffff",
          "texture": "shapes/fonts/rune3/j.png",
          "originX": 0.5,
          "originY": 0.5,
          "values": {"name": ""},
          "groupName": null
        },
        {
          "x": 312,
          "y": 1258,
          "scaleX": 1,
          "scaleY": 1,
          "rotation": 0,
          "tint": "#ffffff",
          "texture": "shapes/fonts/rune3/k.png",
          "originX": 0.5,
          "originY": 0.5,
          "values": {"name": ""},
          "groupName": null
        },
        {
          "x": 376,
          "y": 1256,
          "scaleX": 1,
          "scaleY": 1,
          "rotation": 0,
          "tint": "#ffffff",
          "texture": "shapes/fonts/rune3/l.png",
          "originX": 0.5,
          "originY": 0.5,
          "values": {"name": ""},
          "groupName": null
        },
        {
          "x": 245,
          "y": 1224,
          "scaleX": 1,
          "scaleY": 1,
          "rotation": 0,
          "tint": "#ffffff",
          "texture": "shapes/fonts/weight3/j.png",
          "originX": 0.5,
          "originY": 0.5,
          "values": {"name": ""},
          "groupName": null
        },
        {
          "x": 177,
          "y": 920,
          "scaleX": 1,
          "scaleY": 1,
          "rotation": 0,
          "tint": "#ffffff",
          "texture": "shapes/fonts/rune3/d.png",
          "originX": 0.5,
          "originY": 0.5,
          "values": {"name": ""},
          "groupName": null
        },
        {
          "x": 249,
          "y": 920,
          "scaleX": 1,
          "scaleY": 1,
          "rotation": 0,
          "tint": "#ffffff",
          "texture": "shapes/fonts/rune3/i.png",
          "originX": 0.5,
          "originY": 0.5,
          "values": {"name": ""},
          "groupName": null
        },
        {
          "x": 313,
          "y": 920,
          "scaleX": 1,
          "scaleY": 1,
          "rotation": 0,
          "tint": "#ffffff",
          "texture": "shapes/fonts/rune3/m.png",
          "originX": 0.5,
          "originY": 0.5,
          "values": {"name": ""},
          "groupName": null
        },
        {
          "x": 377,
          "y": 920,
          "scaleX": 1,
          "scaleY": 1,
          "rotation": 0,
          "tint": "#ffffff",
          "texture": "shapes/fonts/rune3/g.png",
          "originX": 0.5,
          "originY": 0.5,
          "values": {"name": ""},
          "groupName": null
        },
        {
          "x": 176,
          "y": 760,
          "scaleX": 1,
          "scaleY": 1,
          "rotation": 0,
          "tint": "#ffffff",
          "texture": "shapes/fonts/rune3/e.png",
          "originX": 0.5,
          "originY": 0.5,
          "values": {"name": ""},
          "groupName": null
        },
        {
          "x": 248,
          "y": 760,
          "scaleX": 1,
          "scaleY": 1,
          "rotation": 0,
          "tint": "#ffffff",
          "texture": "shapes/fonts/rune3/z.png",
          "originX": 0.5,
          "originY": 0.5,
          "values": {"name": ""},
          "groupName": null
        },
        {
          "x": 312,
          "y": 760,
          "scaleX": 1,
          "scaleY": 1,
          "rotation": 0,
          "tint": "#ffffff",
          "texture": "shapes/fonts/rune3/y.png",
          "originX": 0.5,
          "originY": 0.5,
          "values": {"name": ""},
          "groupName": null
        },
        {
          "x": 376,
          "y": 760,
          "scaleX": 1,
          "scaleY": 1,
          "rotation": 0,
          "tint": "#ffffff",
          "texture": "shapes/fonts/rune3/x.png",
          "originX": 0.5,
          "originY": 0.5,
          "values": {"name": ""},
          "groupName": null
        },
        {
          "x": 376,
          "y": 592,
          "scaleX": 1,
          "scaleY": 1,
          "rotation": 0,
          "tint": "#ffffff",
          "texture": "shapes/fonts/rune3/a.png",
          "originX": 0.5,
          "originY": 0.5,
          "values": {"name": ""},
          "groupName": null
        },
        {
          "x": 312,
          "y": 592,
          "scaleX": 1,
          "scaleY": 1,
          "rotation": 0,
          "tint": "#ffffff",
          "texture": "shapes/fonts/rune3/b.png",
          "originX": 0.5,
          "originY": 0.5,
          "values": {"name": ""},
          "groupName": null
        },
        {
          "x": 248,
          "y": 592,
          "scaleX": 1,
          "scaleY": 1,
          "rotation": 0,
          "tint": "#ffffff",
          "texture": "shapes/fonts/rune3/c.png",
          "originX": 0.5,
          "originY": 0.5,
          "values": {"name": ""},
          "groupName": null
        },
        {
          "x": 176,
          "y": 592,
          "scaleX": 1,
          "scaleY": 1,
          "rotation": 0,
          "tint": "#ffffff",
          "texture": "shapes/fonts/rune3/d.png",
          "originX": 0.5,
          "originY": 0.5,
          "values": {"name": ""},
          "groupName": null
        },
        {
          "x": 248,
          "y": 408,
          "scaleX": 1,
          "scaleY": 1,
          "rotation": 0,
          "tint": "#ffffff",
          "texture": "shapes/fonts/rune3/l.png",
          "originX": 0.5,
          "originY": 0.5,
          "values": {"name": ""},
          "groupName": null
        },
        {
          "x": 176,
          "y": 408,
          "scaleX": 1,
          "scaleY": 1,
          "rotation": 0,
          "tint": "#ffffff",
          "texture": "shapes/fonts/rune3/p.png",
          "originX": 0.5,
          "originY": 0.5,
          "values": {"name": ""},
          "groupName": null
        },
        {
          "x": 312,
          "y": 408,
          "scaleX": 1,
          "scaleY": 1,
          "rotation": 0,
          "tint": "#ffffff",
          "texture": "shapes/fonts/rune3/o.png",
          "originX": 0.5,
          "originY": 0.5,
          "values": {"name": ""},
          "groupName": null
        },
        {
          "x": 376,
          "y": 408,
          "scaleX": 1,
          "scaleY": 1,
          "rotation": 0,
          "tint": "#ffffff",
          "texture": "shapes/fonts/rune3/t.png",
          "originX": 0.5,
          "originY": 0.5,
          "values": {"name": ""},
          "groupName": null
        }
      ],
      "folder": "../textures"
    },
    {
      "name": "ParallaxDecals",
      "_eid": "17093961",
      "offsetX": 0,
      "offsetY": 0,
      "gridCellWidth": 8,
      "gridCellHeight": 8,
      "gridCellsX": 64,
      "gridCellsY": 209,
      "decals": [],
      "folder": "../textures"
    }
  ]
}