{
  "ogmoVersion": "3.4.0-hubol",
  "width": 9848,
  "height": 696,
  "offsetX": 0,
  "offsetY": 0,
  "values": {"Terrain Color": "#000000"},
  "backgroundColor": "#408000",
  "layers": [
    {
      "name": "MarkerEntities",
      "_eid": "73166939",
      "offsetX": 0,
      "offsetY": 0,
      "gridCellWidth": 8,
      "gridCellHeight": 8,
      "gridCellsX": 1231,
      "gridCellsY": 87,
      "entities": [
        {
          "name": "Marker",
          "id": 0,
          "_eid": "73148747",
          "x": 215,
          "y": 376,
          "originX": 8,
          "originY": 8,
          "tint": "#00ff00",
          "values": {"name": "PlayerStartMarker", "depth": 0}
        },
        {
          "name": "Marker",
          "id": 1,
          "_eid": "73148747",
          "x": 160,
          "y": 376,
          "originX": 8,
          "originY": 8,
          "tint": "#ff0000",
          "values": {"name": "GhostStartMarker", "depth": 0}
        }
      ]
    },
    {
      "name": "RegionEntities",
      "_eid": "01831167",
      "offsetX": 0,
      "offsetY": 0,
      "gridCellWidth": 8,
      "gridCellHeight": 8,
      "gridCellsX": 1231,
      "gridCellsY": 87,
      "entities": [
        {
          "name": "GateVertical",
          "id": 0,
          "_eid": "64222434",
          "x": 0,
          "y": 656,
          "width": 9864,
          "originX": 0,
          "originY": 0,
          "flippedY": false,
          "values": {"sceneName": "scnRaceTrack", "checkpointName": "fromRestart", "name": "", "depth": 0}
        },
        {
          "name": "Region",
          "id": 1,
          "_eid": "11908607",
          "x": 9640,
          "y": 336,
          "width": 208,
          "height": 120,
          "originX": 0,
          "originY": 0,
          "tint": "#00ff00",
          "values": {"name": "WinRegion", "depth": 0}
        }
      ]
    },
    {
      "name": "FrontDecals",
      "_eid": "17577176",
      "offsetX": 0,
      "offsetY": 0,
      "gridCellWidth": 8,
      "gridCellHeight": 8,
      "gridCellsX": 1231,
      "gridCellsY": 87,
      "decals": [],
      "folder": "../textures"
    },
    {
      "name": "FrontEntities",
      "_eid": "55690179",
      "offsetX": 0,
      "offsetY": 0,
      "gridCellWidth": 8,
      "gridCellHeight": 8,
      "gridCellsX": 1231,
      "gridCellsY": 87,
      "entities": []
    },
    {
      "name": "PlayerEntities",
      "_eid": "96470627",
      "offsetX": 0,
      "offsetY": 0,
      "gridCellWidth": 8,
      "gridCellHeight": 8,
      "gridCellsX": 1231,
      "gridCellsY": 87,
      "entities": [
        {
          "name": "Player",
          "id": 0,
          "_eid": "93092164",
          "x": 216,
          "y": 376,
          "originX": 22,
          "originY": 39,
          "flippedX": false,
          "values": {"name": "", "depth": 0}
        },
        {
          "name": "Checkpoint",
          "id": 4,
          "_eid": "19953026",
          "x": 216,
          "y": 104,
          "originX": 22,
          "originY": 39,
          "flippedX": false,
          "values": {"name": "fromRestart", "depth": 0, "overrideFlipX": "retainFromPreviousScene"}
        }
      ]
    },
    {
      "name": "CharacterEntities",
      "_eid": "07790422",
      "offsetX": 0,
      "offsetY": 0,
      "gridCellWidth": 8,
      "gridCellHeight": 8,
      "gridCellsX": 1231,
      "gridCellsY": 87,
      "entities": []
    },
    {
      "name": "AboveEntitiesDecals",
      "_eid": "63753160",
      "offsetX": 0,
      "offsetY": 0,
      "gridCellWidth": 8,
      "gridCellHeight": 8,
      "gridCellsX": 1231,
      "gridCellsY": 87,
      "decals": [],
      "folder": "../textures"
    },
    {
      "name": "Entities",
      "_eid": "93086020",
      "offsetX": 0,
      "offsetY": 0,
      "gridCellWidth": 8,
      "gridCellHeight": 8,
      "gridCellsX": 1231,
      "gridCellsY": 87,
      "entities": []
    },
    {
      "name": "TerrainDecals",
      "_eid": "02386446",
      "offsetX": 0,
      "offsetY": 0,
      "gridCellWidth": 8,
      "gridCellHeight": 8,
      "gridCellsX": 1231,
      "gridCellsY": 87,
      "decals": [],
      "folder": "../textures"
    },
    {
      "name": "TerrainEntities",
      "_eid": "02302709",
      "offsetX": 0,
      "offsetY": 0,
      "gridCellWidth": 8,
      "gridCellHeight": 8,
      "gridCellsX": 1231,
      "gridCellsY": 87,
      "entities": [
        {
          "name": "Block",
          "id": 0,
          "_eid": "93117141",
          "x": 0,
          "y": 376,
          "width": 392,
          "height": 320,
          "originX": 0,
          "originY": 0,
          "tint": "#000000",
          "values": {"name": "", "depth": 0, "visible": true}
        },
        {
          "name": "Slope",
          "id": 1,
          "_eid": "95675713",
          "x": 392,
          "y": 376,
          "width": 256,
          "height": 128,
          "flippedX": true,
          "flippedY": false,
          "tint": "#000000",
          "values": {"name": "", "depth": 0, "visible": true}
        },
        {
          "name": "Slope",
          "id": 2,
          "_eid": "95675713",
          "x": 648,
          "y": 504,
          "width": 256,
          "height": 64,
          "flippedX": true,
          "flippedY": false,
          "tint": "#000000",
          "values": {"name": "", "depth": 0, "visible": true}
        },
        {
          "name": "Block",
          "id": 3,
          "_eid": "93117141",
          "x": 904,
          "y": 568,
          "width": 1248,
          "height": 56,
          "originX": 0,
          "originY": 0,
          "tint": "#000000",
          "values": {"name": "", "depth": 0, "visible": true}
        },
        {
          "name": "Slope",
          "id": 4,
          "_eid": "95675713",
          "x": 2152,
          "y": 504,
          "width": 256,
          "height": 64,
          "flippedX": false,
          "flippedY": false,
          "tint": "#000000",
          "values": {"name": "", "depth": 0, "visible": true}
        },
        {
          "name": "Slope",
          "id": 5,
          "_eid": "95675713",
          "x": 2408,
          "y": 376,
          "width": 256,
          "height": 128,
          "flippedX": false,
          "flippedY": false,
          "tint": "#000000",
          "values": {"name": "", "depth": 0, "visible": true}
        },
        {
          "name": "Block",
          "id": 6,
          "_eid": "93117141",
          "x": 2664,
          "y": 376,
          "width": 392,
          "height": 320,
          "originX": 0,
          "originY": 0,
          "tint": "#000000",
          "values": {"name": "", "depth": 0, "visible": true}
        },
        {
          "name": "Block",
          "id": 7,
          "_eid": "93117141",
          "x": 1048,
          "y": 512,
          "width": 16,
          "height": 56,
          "originX": 0,
          "originY": 0,
          "tint": "#000000",
          "values": {"name": "", "depth": 0, "visible": true}
        },
        {
          "name": "Block",
          "id": 11,
          "_eid": "93117141",
          "x": 1496,
          "y": 512,
          "width": 16,
          "height": 56,
          "originX": 0,
          "originY": 0,
          "tint": "#000000",
          "values": {"name": "", "depth": 0, "visible": true}
        },
        {
          "name": "Block",
          "id": 23,
          "_eid": "93117141",
          "x": 1944,
          "y": 512,
          "width": 16,
          "height": 56,
          "originX": 0,
          "originY": 0,
          "tint": "#000000",
          "values": {"name": "", "depth": 0, "visible": true}
        },
        {
          "name": "Block",
          "id": 24,
          "_eid": "93117141",
          "x": 544,
          "y": 0,
          "width": 1936,
          "height": 368,
          "originX": 0,
          "originY": 0,
          "tint": "#000000",
          "values": {"name": "", "depth": 0, "visible": true}
        },
        {
          "name": "Block",
          "id": 27,
          "_eid": "93117141",
          "x": 3096,
          "y": -152,
          "width": 2848,
          "height": 376,
          "originX": 0,
          "originY": 0,
          "tint": "#000000",
          "values": {"name": "", "depth": 0, "visible": true}
        },
        {
          "name": "Block",
          "id": 28,
          "_eid": "93117141",
          "x": 3208,
          "y": 376,
          "width": 160,
          "height": 32,
          "originX": 0,
          "originY": 0,
          "tint": "#000000",
          "values": {"name": "", "depth": 0, "visible": true}
        },
        {
          "name": "Block",
          "id": 29,
          "_eid": "93117141",
          "x": 3592,
          "y": 376,
          "width": 160,
          "height": 32,
          "originX": 0,
          "originY": 0,
          "tint": "#000000",
          "values": {"name": "", "depth": 0, "visible": true}
        },
        {
          "name": "Block",
          "id": 30,
          "_eid": "93117141",
          "x": 4032,
          "y": 408,
          "width": 160,
          "height": 32,
          "originX": 0,
          "originY": 0,
          "tint": "#000000",
          "values": {"name": "", "depth": 0, "visible": true}
        },
        {
          "name": "Block",
          "id": 31,
          "_eid": "93117141",
          "x": 4528,
          "y": 416,
          "width": 160,
          "height": 32,
          "originX": 0,
          "originY": 0,
          "tint": "#000000",
          "values": {"name": "", "depth": 0, "visible": true}
        },
        {
          "name": "Block",
          "id": 32,
          "_eid": "93117141",
          "x": 4976,
          "y": 512,
          "width": 160,
          "height": 32,
          "originX": 0,
          "originY": 0,
          "tint": "#000000",
          "values": {"name": "", "depth": 0, "visible": true}
        },
        {
          "name": "Block",
          "id": 33,
          "_eid": "93117141",
          "x": 5448,
          "y": 520,
          "width": 160,
          "height": 32,
          "originX": 0,
          "originY": 0,
          "tint": "#000000",
          "values": {"name": "", "depth": 0, "visible": true}
        },
        {
          "name": "Block",
          "id": 35,
          "_eid": "93117141",
          "x": 3536,
          "y": 224,
          "width": 264,
          "height": 40,
          "originX": 0,
          "originY": 0,
          "tint": "#000000",
          "values": {"name": "", "depth": 0, "visible": true}
        },
        {
          "name": "Block",
          "id": 36,
          "_eid": "93117141",
          "x": 3984,
          "y": 224,
          "width": 264,
          "height": 40,
          "originX": 0,
          "originY": 0,
          "tint": "#000000",
          "values": {"name": "", "depth": 0, "visible": true}
        },
        {
          "name": "Block",
          "id": 37,
          "_eid": "93117141",
          "x": 4480,
          "y": 224,
          "width": 264,
          "height": 72,
          "originX": 0,
          "originY": 0,
          "tint": "#000000",
          "values": {"name": "", "depth": 0, "visible": true}
        },
        {
          "name": "Block",
          "id": 38,
          "_eid": "93117141",
          "x": 4936,
          "y": 224,
          "width": 264,
          "height": 104,
          "originX": 0,
          "originY": 0,
          "tint": "#000000",
          "values": {"name": "", "depth": 0, "visible": true}
        },
        {
          "name": "Block",
          "id": 39,
          "_eid": "93117141",
          "x": 5400,
          "y": 224,
          "width": 264,
          "height": 104,
          "originX": 0,
          "originY": 0,
          "tint": "#000000",
          "values": {"name": "", "depth": 0, "visible": true}
        },
        {
          "name": "Block",
          "id": 40,
          "_eid": "93117141",
          "x": 5920,
          "y": 608,
          "width": 1528,
          "height": 88,
          "originX": 0,
          "originY": 0,
          "tint": "#000000",
          "values": {"name": "", "depth": 0, "visible": true}
        },
        {
          "name": "Pipe",
          "id": 41,
          "_eid": "95769929",
          "x": 6240,
          "y": 552,
          "width": 952,
          "values": {"name": "", "visible": true, "depth": 0}
        },
        {
          "name": "Block",
          "id": 42,
          "_eid": "93117141",
          "x": 6144,
          "y": 0,
          "width": 96,
          "height": 560,
          "originX": 0,
          "originY": 0,
          "tint": "#000000",
          "values": {"name": "", "depth": 0, "visible": true}
        },
        {
          "name": "Block",
          "id": 43,
          "_eid": "93117141",
          "x": 6240,
          "y": 552,
          "width": 240,
          "height": 16,
          "originX": 0,
          "originY": 0,
          "tint": "#000000",
          "values": {"name": "", "depth": 0, "visible": true}
        },
        {
          "name": "Pipe",
          "id": 44,
          "_eid": "95769929",
          "x": 6240,
          "y": 496,
          "width": 952,
          "values": {"name": "", "visible": true, "depth": 0}
        },
        {
          "name": "Block",
          "id": 45,
          "_eid": "93117141",
          "x": 6240,
          "y": 496,
          "width": 512,
          "height": 16,
          "originX": 0,
          "originY": 0,
          "tint": "#000000",
          "values": {"name": "", "depth": 0, "visible": true}
        },
        {
          "name": "Block",
          "id": 46,
          "_eid": "93117141",
          "x": 7032,
          "y": 496,
          "width": 544,
          "height": 112,
          "originX": 0,
          "originY": 0,
          "tint": "#000000",
          "values": {"name": "", "depth": 0, "visible": true}
        },
        {
          "name": "Block",
          "id": 47,
          "_eid": "93117141",
          "x": 6736,
          "y": 552,
          "width": 304,
          "height": 56,
          "originX": 0,
          "originY": 0,
          "tint": "#000000",
          "values": {"name": "", "depth": 0, "visible": true}
        },
        {
          "name": "Pipe",
          "id": 48,
          "_eid": "95769929",
          "x": 7416,
          "y": 440,
          "width": 1984,
          "values": {"name": "", "visible": true, "depth": 0}
        },
        {
          "name": "Block",
          "id": 49,
          "_eid": "93117141",
          "x": 6280,
          "y": 440,
          "width": 1136,
          "height": 16,
          "originX": 0,
          "originY": 0,
          "tint": "#000000",
          "values": {"name": "", "depth": 0, "visible": true}
        },
        {
          "name": "Block",
          "id": 50,
          "_eid": "93117141",
          "x": 7576,
          "y": 400,
          "width": 504,
          "height": 56,
          "originX": 0,
          "originY": 0,
          "tint": "#000000",
          "values": {"name": "", "depth": 0, "visible": true}
        },
        {
          "name": "Pipe",
          "id": 51,
          "_eid": "95769929",
          "x": 7992,
          "y": 496,
          "width": 712,
          "values": {"name": "", "visible": true, "depth": 0}
        },
        {
          "name": "Block",
          "id": 53,
          "_eid": "93117141",
          "x": 7904,
          "y": 456,
          "width": 176,
          "height": 56,
          "originX": 0,
          "originY": 0,
          "tint": "#000000",
          "values": {"name": "", "depth": 0, "visible": true}
        },
        {
          "name": "Block",
          "id": 54,
          "_eid": "93117141",
          "x": 8248,
          "y": 496,
          "width": 288,
          "height": 72,
          "originX": 0,
          "originY": 0,
          "tint": "#000000",
          "values": {"name": "", "depth": 0, "visible": true}
        },
        {
          "name": "Block",
          "id": 55,
          "_eid": "93117141",
          "x": 8080,
          "y": 440,
          "width": 368,
          "height": 16,
          "originX": 0,
          "originY": 0,
          "tint": "#000000",
          "values": {"name": "", "depth": 0, "visible": true}
        },
        {
          "name": "Block",
          "id": 56,
          "_eid": "93117141",
          "x": 7576,
          "y": 0,
          "width": 504,
          "height": 408,
          "originX": 0,
          "originY": 0,
          "tint": "#000000",
          "values": {"name": "", "depth": 0, "visible": true}
        },
        {
          "name": "Pipe",
          "id": 57,
          "_eid": "95769929",
          "x": 7936,
          "y": 552,
          "width": 176,
          "values": {"name": "", "visible": true, "depth": 0}
        },
        {
          "name": "Pipe",
          "id": 58,
          "_eid": "95769929",
          "x": 7576,
          "y": 552,
          "width": 256,
          "values": {"name": "", "visible": true, "depth": 0}
        },
        {
          "name": "Block",
          "id": 59,
          "_eid": "93117141",
          "x": 9640,
          "y": 440,
          "width": 232,
          "height": 256,
          "originX": 0,
          "originY": 0,
          "tint": "#000000",
          "values": {"name": "", "depth": 0, "visible": true}
        },
        {
          "name": "Block",
          "id": 60,
          "_eid": "93117141",
          "x": 1032,
          "y": 512,
          "width": 16,
          "height": 16,
          "originX": 0,
          "originY": 0,
          "tint": "#000000",
          "values": {"name": "", "depth": 0, "visible": true}
        },
        {
          "name": "Block",
          "id": 61,
          "_eid": "93117141",
          "x": 1480,
          "y": 512,
          "width": 16,
          "height": 16,
          "originX": 0,
          "originY": 0,
          "tint": "#000000",
          "values": {"name": "", "depth": 0, "visible": true}
        },
        {
          "name": "Block",
          "id": 62,
          "_eid": "93117141",
          "x": 1928,
          "y": 512,
          "width": 16,
          "height": 16,
          "originX": 0,
          "originY": 0,
          "tint": "#000000",
          "values": {"name": "", "depth": 0, "visible": true}
        }
      ]
    },
    {
      "name": "BackgroundEntities",
      "_eid": "41483982",
      "offsetX": 0,
      "offsetY": 0,
      "gridCellWidth": 8,
      "gridCellHeight": 8,
      "gridCellsX": 1231,
      "gridCellsY": 87,
      "entities": []
    },
    {
      "name": "BackgroundDecals",
      "_eid": "64691217",
      "offsetX": 0,
      "offsetY": 0,
      "gridCellWidth": 8,
      "gridCellHeight": 8,
      "gridCellsX": 1231,
      "gridCellsY": 87,
      "decals": [],
      "folder": "../textures"
    },
    {
      "name": "ParallaxDecals",
      "_eid": "17093961",
      "offsetX": 0,
      "offsetY": 0,
      "gridCellWidth": 8,
      "gridCellHeight": 8,
      "gridCellsX": 1231,
      "gridCellsY": 87,
      "decals": [],
      "folder": "../textures"
    }
  ]
}